rotastellar_compute/__init__.py
rotastellar_compute/feasibility.py
rotastellar_compute/latency.py
rotastellar_compute/power.py
rotastellar_compute/thermal.py
rotastellar_compute-0.1.1.dist-info/METADATA
rotastellar_compute-0.1.1.dist-info/WHEEL
rotastellar_compute-0.1.1.dist-info/licenses/LICENSE
rotastellar_compute-0.1.1.dist-info/RECORD
