Metadata-Version: 2.4
Name: rotastellar-compute
Version: 0.1.1
Summary: Orbital compute planning and simulation tools
Project-URL: Homepage, https://rotastellar.com/products/orbital-compute
Project-URL: Documentation, https://rotastellar.com/docs/compute
Project-URL: Repository, https://github.com/rotastellar/rotastellar-python
Author-email: Subhadip Mitra <subhadipmitra@rotastellar.com>, RotaStellar Research <research@rotastellar.com>
Maintainer-email: Subhadip Mitra <subhadipmitra@rotastellar.com>, RotaStellar Research <research@rotastellar.com>
License: MIT
License-File: LICENSE
Keywords: data-center,orbital,space,space-computing,thermal-simulation
Classifier: Development Status :: 3 - Alpha
Classifier: Intended Audience :: Developers
Classifier: Intended Audience :: Science/Research
Classifier: License :: OSI Approved :: MIT License
Classifier: Programming Language :: Python :: 3
Classifier: Programming Language :: Python :: 3.9
Classifier: Programming Language :: Python :: 3.10
Classifier: Programming Language :: Python :: 3.11
Classifier: Programming Language :: Python :: 3.12
Classifier: Topic :: Scientific/Engineering :: Astronomy
Classifier: Topic :: Scientific/Engineering :: Physics
Requires-Python: >=3.9
Requires-Dist: rotastellar>=0.1.0
Provides-Extra: dev
Requires-Dist: pytest-cov>=4.0; extra == 'dev'
Requires-Dist: pytest>=7.0; extra == 'dev'
Provides-Extra: numpy
Requires-Dist: numpy>=1.24; extra == 'numpy'
